myally_database.py
myally_database-1.3.dist-info/METADATA
myally_database-1.3.dist-info/WHEEL
myally_database-1.3.dist-info/RECORD
