Metadata-Version: 2.1
Name: myally_database
Version: 1.3
Summary: 简单的数据库连接
Home-page: https://github.com/myally/myally_database
License: MIT
Author: BlackWhite
Author-email: jierong8215@gmail.com
Requires-Python: >=3.6
Classifier: License :: OSI Approved :: MIT License
Classifier: Programming Language :: Python :: 3
Classifier: Programming Language :: Python :: 3.6
Classifier: Programming Language :: Python :: 3.7
Classifier: Programming Language :: Python :: 3.8
Classifier: Programming Language :: Python :: 3.9
Classifier: Programming Language :: Python :: 3.10
Classifier: Programming Language :: Python :: 3.11
Requires-Dist: SQLAlchemy (==1.4.47)
Project-URL: Repository, https://github.com/myally/myally_database
